{
  "event_id": "019caf39-18ab-70f2-8ecc-400d6a9db951",
  "occurred_at": "2026-03-02T15:44:40.61971Z",
  "type": "idx.knot_head",
  "data": {
    "deferred_from_state": null,
    "knot_id": "foolery-198d",
    "profile_id": "autopilot",
    "state": "implementation",
    "terminal": false,
    "title": "Replace kno update --status with kno next in enforceQueueTerminalInvariant",
    "updated_at": "2026-03-02T15:44:40.61971Z"
  },
  "precondition": {
    "profile_etag": "019caf39-0670-7f13-8803-5ed4bdda9457"
  }
}
