{
  "event_id": "019cd914-3bb2-7983-b7a9-82d335d5270e",
  "occurred_at": "2026-03-10T18:48:27.815401Z",
  "type": "idx.knot_head",
  "data": {
    "deferred_from_state": null,
    "gate": {
      "owner_kind": "agent"
    },
    "invariants": [],
    "knot_id": "foolery-9c91",
    "profile_id": "autopilot",
    "state": "ready_for_implementation",
    "terminal": false,
    "title": "migrate rollbackBeatState to use kno rb",
    "type": "work",
    "updated_at": "2026-03-10T18:48:27.815401Z"
  }
}
